[
  {
    "step": 0,
    "timestamp": "2026-01-11T12:55:05.386207",
    "path": [],
    "action": "initial_load",
    "url": "https://www.zara.com/us/",
    "new_buttons": [],
    "new_links": {},
    "aria_length": 14506,
    "aria_preview": "- link \"Skip to main content\":\n  - /url: \"#main\"\n- banner:\n  - button \"Open Menu\":\n    - img\n  - link \"Go to homepage\":\n    - /url: https://www.zara.com/us/\n  - list:\n    - listitem:\n      - link \"Search\":\n        - /url: https://www.zara.com/us/en/search/home\n    - listitem:\n      - link \"LOG IN\":\n        - /url: https://www.zara.com/us/en/logon\n    - listitem:\n      - link \"Help\":\n        - /url: https://www.zara.com/us/en/help-center\n    - listitem:\n      - link \"Cart empty\":\n        - /url: ..."
  },
  {
    "step": 1,
    "timestamp": "2026-01-11T12:55:52.118497",
    "path": [
      "WOMAN"
    ],
    "action": "clicked: WOMAN",
    "url": "https://www.zara.com/us/",
    "new_buttons": [],
    "new_links": {
      "Go to homepage": "https://www.zara.com/us/",
      "LOG IN": "https://www.zara.com/us/en/logon",
      "Help": "https://www.zara.com/us/en/help-center",
      "GIFT CARD": "https://www.zara.com/us/en/z-giftcard-mkt1394.html",
      "CAREERS": "https://www.zara.com/us/en/work-with-us-mkt8081.html",
      "JOIN LIFE": "https://www.zara.com/us/en/z-join-life-mkt1399.html",
      "STORES": "https://www.zara.com/us/en/z-stores-st1404.html",
      "PERFUMES": "https://www.zara.com/us/en/woman-accessories-perfumes-l1017.html?v1=2419833",
      "MAKEUP": "https://www.zara.com/us/en/woman-beauty-makeup-l4414.html?v1=1881272",
      "ZARA HAIR": "https://www.zara.com/us/en/woman-hair-l7345.html?v1=2418886",
      "ABOUT": "https://www.zara.com/us/en/zara-travel-about-mkt15716.html",
      "REPAIR": "https://www.zara.com/us/en/preowned-repair-mkt5796.html",
      "SECOND HAND": "https://www.zara.com/us/en/preowned-resell-mkt5797.html",
      "DONATE": "https://www.zara.com/us/en/preowned-donate-mkt5798.html",
      "THE GUIDES": "https://www.zara.com/us/en/zara-travel-guide-mkt15717.html",
      "Youtube": "http://www.youtube.com/user/zara",
      "Spotify": "https://open.spotify.com/user/r6ivwuv0ebk346hhxo446pbfv"
    },
    "aria_length": 19035,
    "aria_preview": "- link \"Skip to main content\":\n  - /url: \"#main\"\n- banner:\n  - button \"Close menu\"\n  - link \"Go to homepage\":\n    - /url: https://www.zara.com/us/\n  - list:\n    - listitem:\n      - link \"Search\":\n        - /url: https://www.zara.com/us/en/search/home\n    - listitem:\n      - link \"LOG IN\":\n        - /url: https://www.zara.com/us/en/logon\n    - listitem:\n      - link \"Help\":\n        - /url: https://www.zara.com/us/en/help-center\n    - listitem:\n      - link \"Cart empty\":\n        - /url: https://ww..."
  },
  {
    "step": 2,
    "timestamp": "2026-01-11T12:55:58.289213",
    "path": [
      "MAN"
    ],
    "action": "clicked: MAN",
    "url": "https://www.zara.com/us/",
    "new_buttons": [],
    "new_links": {
      "Go to homepage": "https://www.zara.com/us/",
      "LOG IN": "https://www.zara.com/us/en/logon",
      "Help": "https://www.zara.com/us/en/help-center",
      "GIFT CARD": "https://www.zara.com/us/en/z-giftcard-mkt1394.html",
      "CAREERS": "https://www.zara.com/us/en/work-with-us-mkt8081.html",
      "JOIN LIFE": "https://www.zara.com/us/en/z-join-life-mkt1399.html",
      "STORES": "https://www.zara.com/us/en/z-stores-st1404.html",
      "PERFUMES": "https://www.zara.com/us/en/woman-accessories-perfumes-l1017.html?v1=2419833",
      "MAKEUP": "https://www.zara.com/us/en/woman-beauty-makeup-l4414.html?v1=1881272",
      "ZARA HAIR": "https://www.zara.com/us/en/woman-hair-l7345.html?v1=2418886",
      "ABOUT": "https://www.zara.com/us/en/zara-travel-about-mkt15716.html",
      "REPAIR": "https://www.zara.com/us/en/preowned-repair-mkt5796.html",
      "SECOND HAND": "https://www.zara.com/us/en/preowned-resell-mkt5797.html",
      "DONATE": "https://www.zara.com/us/en/preowned-donate-mkt5798.html",
      "THE GUIDES": "https://www.zara.com/us/en/zara-travel-guide-mkt15717.html",
      "Youtube": "http://www.youtube.com/user/zara",
      "Spotify": "https://open.spotify.com/user/r6ivwuv0ebk346hhxo446pbfv"
    },
    "aria_length": 19310,
    "aria_preview": "- link \"Skip to main content\":\n  - /url: \"#main\"\n- banner:\n  - button \"Close menu\"\n  - link \"Go to homepage\":\n    - /url: https://www.zara.com/us/\n  - list:\n    - listitem:\n      - link \"Search\":\n        - /url: https://www.zara.com/us/en/search/home\n    - listitem:\n      - link \"LOG IN\":\n        - /url: https://www.zara.com/us/en/logon\n    - listitem:\n      - link \"Help\":\n        - /url: https://www.zara.com/us/en/help-center\n    - listitem:\n      - link \"Cart empty\":\n        - /url: https://ww..."
  },
  {
    "step": 3,
    "timestamp": "2026-01-11T12:56:02.764975",
    "path": [
      "KIDS"
    ],
    "action": "clicked: KIDS",
    "url": "https://www.zara.com/us/",
    "new_buttons": [],
    "new_links": {
      "Go to homepage": "https://www.zara.com/us/",
      "LOG IN": "https://www.zara.com/us/en/logon",
      "Help": "https://www.zara.com/us/en/help-center",
      "GIFT CARD": "https://www.zara.com/us/en/z-giftcard-mkt1394.html",
      "CAREERS": "https://www.zara.com/us/en/work-with-us-mkt8081.html",
      "JOIN LIFE": "https://www.zara.com/us/en/z-join-life-mkt1399.html",
      "STORES": "https://www.zara.com/us/en/z-stores-st1404.html",
      "PERFUMES": "https://www.zara.com/us/en/woman-accessories-perfumes-l1017.html?v1=2419833",
      "MAKEUP": "https://www.zara.com/us/en/woman-beauty-makeup-l4414.html?v1=1881272",
      "ZARA HAIR": "https://www.zara.com/us/en/woman-hair-l7345.html?v1=2418886",
      "ABOUT": "https://www.zara.com/us/en/zara-travel-about-mkt15716.html",
      "REPAIR": "https://www.zara.com/us/en/preowned-repair-mkt5796.html",
      "SECOND HAND": "https://www.zara.com/us/en/preowned-resell-mkt5797.html",
      "DONATE": "https://www.zara.com/us/en/preowned-donate-mkt5798.html",
      "THE GUIDES": "https://www.zara.com/us/en/zara-travel-guide-mkt15717.html",
      "Youtube": "http://www.youtube.com/user/zara",
      "Spotify": "https://open.spotify.com/user/r6ivwuv0ebk346hhxo446pbfv"
    },
    "aria_length": 19309,
    "aria_preview": "- link \"Skip to main content\":\n  - /url: \"#main\"\n- banner:\n  - button \"Close menu\"\n  - link \"Go to homepage\":\n    - /url: https://www.zara.com/us/\n  - list:\n    - listitem:\n      - link \"Search\":\n        - /url: https://www.zara.com/us/en/search/home\n    - listitem:\n      - link \"LOG IN\":\n        - /url: https://www.zara.com/us/en/logon\n    - listitem:\n      - link \"Help\":\n        - /url: https://www.zara.com/us/en/help-center\n    - listitem:\n      - link \"Cart empty\":\n        - /url: https://ww..."
  },
  {
    "step": 4,
    "timestamp": "2026-01-11T12:56:06.710729",
    "path": [
      "ZARA HOME"
    ],
    "action": "clicked: ZARA HOME",
    "url": "https://www.zara.com/us/",
    "new_buttons": [],
    "new_links": {
      "Go to homepage": "https://www.zara.com/us/",
      "LOG IN": "https://www.zara.com/us/en/logon",
      "Help": "https://www.zara.com/us/en/help-center",
      "GIFT CARD": "https://www.zara.com/us/en/z-giftcard-mkt1394.html",
      "CAREERS": "https://www.zara.com/us/en/work-with-us-mkt8081.html",
      "JOIN LIFE": "https://www.zara.com/us/en/z-join-life-mkt1399.html",
      "STORES": "https://www.zara.com/us/en/z-stores-st1404.html",
      "PERFUMES": "https://www.zara.com/us/en/woman-accessories-perfumes-l1017.html?v1=2419833",
      "MAKEUP": "https://www.zara.com/us/en/woman-beauty-makeup-l4414.html?v1=1881272",
      "ZARA HAIR": "https://www.zara.com/us/en/woman-hair-l7345.html?v1=2418886",
      "ABOUT": "https://www.zara.com/us/en/zara-travel-about-mkt15716.html",
      "REPAIR": "https://www.zara.com/us/en/preowned-repair-mkt5796.html",
      "SECOND HAND": "https://www.zara.com/us/en/preowned-resell-mkt5797.html",
      "DONATE": "https://www.zara.com/us/en/preowned-donate-mkt5798.html",
      "THE GUIDES": "https://www.zara.com/us/en/zara-travel-guide-mkt15717.html",
      "Youtube": "http://www.youtube.com/user/zara",
      "Spotify": "https://open.spotify.com/user/r6ivwuv0ebk346hhxo446pbfv"
    },
    "aria_length": 19242,
    "aria_preview": "- link \"Skip to main content\":\n  - /url: \"#main\"\n- banner:\n  - button \"Close menu\"\n  - link \"Go to homepage\":\n    - /url: https://www.zara.com/us/\n  - list:\n    - listitem:\n      - link \"Search\":\n        - /url: https://www.zara.com/us/en/search/home\n    - listitem:\n      - link \"LOG IN\":\n        - /url: https://www.zara.com/us/en/logon\n    - listitem:\n      - link \"Help\":\n        - /url: https://www.zara.com/us/en/help-center\n    - listitem:\n      - link \"Cart empty\":\n        - /url: https://ww..."
  },
  {
    "step": 5,
    "timestamp": "2026-01-11T12:56:11.005314",
    "path": [
      "BEAUTY"
    ],
    "action": "clicked: BEAUTY",
    "url": "https://www.zara.com/us/",
    "new_buttons": [],
    "new_links": {
      "Go to homepage": "https://www.zara.com/us/",
      "LOG IN": "https://www.zara.com/us/en/logon",
      "Help": "https://www.zara.com/us/en/help-center",
      "GIFT CARD": "https://www.zara.com/us/en/z-giftcard-mkt1394.html",
      "CAREERS": "https://www.zara.com/us/en/work-with-us-mkt8081.html",
      "JOIN LIFE": "https://www.zara.com/us/en/z-join-life-mkt1399.html",
      "STORES": "https://www.zara.com/us/en/z-stores-st1404.html",
      "PERFUMES": "https://www.zara.com/us/en/woman-accessories-perfumes-l1017.html?v1=2419833",
      "MAKEUP": "https://www.zara.com/us/en/woman-beauty-makeup-l4414.html?v1=1881272",
      "ZARA HAIR": "https://www.zara.com/us/en/woman-hair-l7345.html?v1=2418886",
      "ABOUT": "https://www.zara.com/us/en/zara-travel-about-mkt15716.html",
      "REPAIR": "https://www.zara.com/us/en/preowned-repair-mkt5796.html",
      "SECOND HAND": "https://www.zara.com/us/en/preowned-resell-mkt5797.html",
      "DONATE": "https://www.zara.com/us/en/preowned-donate-mkt5798.html",
      "THE GUIDES": "https://www.zara.com/us/en/zara-travel-guide-mkt15717.html",
      "Youtube": "http://www.youtube.com/user/zara",
      "Spotify": "https://open.spotify.com/user/r6ivwuv0ebk346hhxo446pbfv"
    },
    "aria_length": 19588,
    "aria_preview": "- link \"Skip to main content\":\n  - /url: \"#main\"\n- banner:\n  - button \"Close menu\"\n  - link \"Go to homepage\":\n    - /url: https://www.zara.com/us/\n  - list:\n    - listitem:\n      - link \"Search\":\n        - /url: https://www.zara.com/us/en/search/home\n    - listitem:\n      - link \"LOG IN\":\n        - /url: https://www.zara.com/us/en/logon\n    - listitem:\n      - link \"Help\":\n        - /url: https://www.zara.com/us/en/help-center\n    - listitem:\n      - link \"Cart empty\":\n        - /url: https://ww..."
  },
  {
    "step": 6,
    "timestamp": "2026-01-11T12:56:15.157800",
    "path": [
      "MASSIMO DUTTI"
    ],
    "action": "clicked: MASSIMO DUTTI",
    "url": "https://www.zara.com/us/",
    "new_buttons": [],
    "new_links": {
      "Go to homepage": "https://www.zara.com/us/",
      "LOG IN": "https://www.zara.com/us/en/logon",
      "Help": "https://www.zara.com/us/en/help-center",
      "GIFT CARD": "https://www.zara.com/us/en/z-giftcard-mkt1394.html",
      "CAREERS": "https://www.zara.com/us/en/work-with-us-mkt8081.html",
      "JOIN LIFE": "https://www.zara.com/us/en/z-join-life-mkt1399.html",
      "STORES": "https://www.zara.com/us/en/z-stores-st1404.html",
      "PERFUMES": "https://www.zara.com/us/en/woman-accessories-perfumes-l1017.html?v1=2419833",
      "MAKEUP": "https://www.zara.com/us/en/woman-beauty-makeup-l4414.html?v1=1881272",
      "ZARA HAIR": "https://www.zara.com/us/en/woman-hair-l7345.html?v1=2418886",
      "ABOUT": "https://www.zara.com/us/en/zara-travel-about-mkt15716.html",
      "REPAIR": "https://www.zara.com/us/en/preowned-repair-mkt5796.html",
      "SECOND HAND": "https://www.zara.com/us/en/preowned-resell-mkt5797.html",
      "DONATE": "https://www.zara.com/us/en/preowned-donate-mkt5798.html",
      "THE GUIDES": "https://www.zara.com/us/en/zara-travel-guide-mkt15717.html",
      "Youtube": "http://www.youtube.com/user/zara",
      "Spotify": "https://open.spotify.com/user/r6ivwuv0ebk346hhxo446pbfv"
    },
    "aria_length": 19182,
    "aria_preview": "- link \"Skip to main content\":\n  - /url: \"#main\"\n- banner:\n  - button \"Close menu\"\n  - link \"Go to homepage\":\n    - /url: https://www.zara.com/us/\n  - list:\n    - listitem:\n      - link \"Search\":\n        - /url: https://www.zara.com/us/en/search/home\n    - listitem:\n      - link \"LOG IN\":\n        - /url: https://www.zara.com/us/en/logon\n    - listitem:\n      - link \"Help\":\n        - /url: https://www.zara.com/us/en/help-center\n    - listitem:\n      - link \"Cart empty\":\n        - /url: https://ww..."
  },
  {
    "step": 7,
    "timestamp": "2026-01-11T12:56:20.192044",
    "path": [
      "MASSIMO DUTTI",
      "WOMAN"
    ],
    "action": "clicked: MASSIMO DUTTI > WOMAN",
    "url": "https://www.zara.com/us/",
    "new_buttons": [],
    "new_links": {
      "Go to homepage": "https://www.zara.com/us/",
      "LOG IN": "https://www.zara.com/us/en/logon",
      "Help": "https://www.zara.com/us/en/help-center",
      "GIFT CARD": "https://www.zara.com/us/en/z-giftcard-mkt1394.html",
      "CAREERS": "https://www.zara.com/us/en/work-with-us-mkt8081.html",
      "JOIN LIFE": "https://www.zara.com/us/en/z-join-life-mkt1399.html",
      "STORES": "https://www.zara.com/us/en/z-stores-st1404.html",
      "PERFUMES": "https://www.zara.com/us/en/woman-accessories-perfumes-l1017.html?v1=2419833",
      "MAKEUP": "https://www.zara.com/us/en/woman-beauty-makeup-l4414.html?v1=1881272",
      "ZARA HAIR": "https://www.zara.com/us/en/woman-hair-l7345.html?v1=2418886",
      "ABOUT": "https://www.zara.com/us/en/zara-travel-about-mkt15716.html",
      "REPAIR": "https://www.zara.com/us/en/preowned-repair-mkt5796.html",
      "SECOND HAND": "https://www.zara.com/us/en/preowned-resell-mkt5797.html",
      "DONATE": "https://www.zara.com/us/en/preowned-donate-mkt5798.html",
      "THE GUIDES": "https://www.zara.com/us/en/zara-travel-guide-mkt15717.html",
      "Youtube": "http://www.youtube.com/user/zara",
      "Spotify": "https://open.spotify.com/user/r6ivwuv0ebk346hhxo446pbfv"
    },
    "aria_length": 19184,
    "aria_preview": "- link \"Skip to main content\":\n  - /url: \"#main\"\n- banner:\n  - button \"Close menu\"\n  - link \"Go to homepage\":\n    - /url: https://www.zara.com/us/\n  - list:\n    - listitem:\n      - link \"Search\":\n        - /url: https://www.zara.com/us/en/search/home\n    - listitem:\n      - link \"LOG IN\":\n        - /url: https://www.zara.com/us/en/logon\n    - listitem:\n      - link \"Help\":\n        - /url: https://www.zara.com/us/en/help-center\n    - listitem:\n      - link \"Cart empty\":\n        - /url: https://ww..."
  },
  {
    "step": 8,
    "timestamp": "2026-01-11T12:56:24.244889",
    "path": [
      "MASSIMO DUTTI",
      "MAN"
    ],
    "action": "clicked: MASSIMO DUTTI > MAN",
    "url": "https://www.zara.com/us/",
    "new_buttons": [],
    "new_links": {
      "Go to homepage": "https://www.zara.com/us/",
      "LOG IN": "https://www.zara.com/us/en/logon",
      "Help": "https://www.zara.com/us/en/help-center",
      "GIFT CARD": "https://www.zara.com/us/en/z-giftcard-mkt1394.html",
      "CAREERS": "https://www.zara.com/us/en/work-with-us-mkt8081.html",
      "JOIN LIFE": "https://www.zara.com/us/en/z-join-life-mkt1399.html",
      "STORES": "https://www.zara.com/us/en/z-stores-st1404.html",
      "PERFUMES": "https://www.zara.com/us/en/woman-accessories-perfumes-l1017.html?v1=2419833",
      "MAKEUP": "https://www.zara.com/us/en/woman-beauty-makeup-l4414.html?v1=1881272",
      "ZARA HAIR": "https://www.zara.com/us/en/woman-hair-l7345.html?v1=2418886",
      "ABOUT": "https://www.zara.com/us/en/zara-travel-about-mkt15716.html",
      "REPAIR": "https://www.zara.com/us/en/preowned-repair-mkt5796.html",
      "SECOND HAND": "https://www.zara.com/us/en/preowned-resell-mkt5797.html",
      "DONATE": "https://www.zara.com/us/en/preowned-donate-mkt5798.html",
      "THE GUIDES": "https://www.zara.com/us/en/zara-travel-guide-mkt15717.html",
      "Youtube": "http://www.youtube.com/user/zara",
      "Spotify": "https://open.spotify.com/user/r6ivwuv0ebk346hhxo446pbfv"
    },
    "aria_length": 19459,
    "aria_preview": "- link \"Skip to main content\":\n  - /url: \"#main\"\n- banner:\n  - button \"Close menu\"\n  - link \"Go to homepage\":\n    - /url: https://www.zara.com/us/\n  - list:\n    - listitem:\n      - link \"Search\":\n        - /url: https://www.zara.com/us/en/search/home\n    - listitem:\n      - link \"LOG IN\":\n        - /url: https://www.zara.com/us/en/logon\n    - listitem:\n      - link \"Help\":\n        - /url: https://www.zara.com/us/en/help-center\n    - listitem:\n      - link \"Cart empty\":\n        - /url: https://ww..."
  },
  {
    "step": 9,
    "timestamp": "2026-01-11T12:56:27.589933",
    "path": [
      "ZARA PRE-OWNED"
    ],
    "action": "clicked: ZARA PRE-OWNED",
    "url": "https://www.zara.com/us/",
    "new_buttons": [],
    "new_links": {
      "Go to homepage": "https://www.zara.com/us/",
      "LOG IN": "https://www.zara.com/us/en/logon",
      "Help": "https://www.zara.com/us/en/help-center",
      "GIFT CARD": "https://www.zara.com/us/en/z-giftcard-mkt1394.html",
      "CAREERS": "https://www.zara.com/us/en/work-with-us-mkt8081.html",
      "JOIN LIFE": "https://www.zara.com/us/en/z-join-life-mkt1399.html",
      "STORES": "https://www.zara.com/us/en/z-stores-st1404.html",
      "PERFUMES": "https://www.zara.com/us/en/woman-accessories-perfumes-l1017.html?v1=2419833",
      "MAKEUP": "https://www.zara.com/us/en/woman-beauty-makeup-l4414.html?v1=1881272",
      "ZARA HAIR": "https://www.zara.com/us/en/woman-hair-l7345.html?v1=2418886",
      "ABOUT": "https://www.zara.com/us/en/zara-travel-about-mkt15716.html",
      "REPAIR": "https://www.zara.com/us/en/preowned-repair-mkt5796.html",
      "SECOND HAND": "https://www.zara.com/us/en/preowned-resell-mkt5797.html",
      "DONATE": "https://www.zara.com/us/en/preowned-donate-mkt5798.html",
      "THE GUIDES": "https://www.zara.com/us/en/zara-travel-guide-mkt15717.html",
      "Youtube": "http://www.youtube.com/user/zara",
      "Spotify": "https://open.spotify.com/user/r6ivwuv0ebk346hhxo446pbfv"
    },
    "aria_length": 19424,
    "aria_preview": "- link \"Skip to main content\":\n  - /url: \"#main\"\n- banner:\n  - button \"Close menu\"\n  - link \"Go to homepage\":\n    - /url: https://www.zara.com/us/\n  - list:\n    - listitem:\n      - link \"Search\":\n        - /url: https://www.zara.com/us/en/search/home\n    - listitem:\n      - link \"LOG IN\":\n        - /url: https://www.zara.com/us/en/logon\n    - listitem:\n      - link \"Help\":\n        - /url: https://www.zara.com/us/en/help-center\n    - listitem:\n      - link \"Cart empty\":\n        - /url: https://ww..."
  },
  {
    "step": 10,
    "timestamp": "2026-01-11T12:56:31.788052",
    "path": [
      "TRAVEL MODE"
    ],
    "action": "clicked: TRAVEL MODE",
    "url": "https://www.zara.com/us/en/-c2577013.html?regionGroupId=41",
    "new_buttons": [],
    "new_links": {
      "Go to homepage": "https://www.zara.com/us/",
      "LOG IN": "https://www.zara.com/us/en/logon",
      "Help": "https://www.zara.com/us/en/help-center",
      "GIFT CARD": "https://www.zara.com/us/en/z-giftcard-mkt1394.html",
      "CAREERS": "https://www.zara.com/us/en/work-with-us-mkt8081.html",
      "JOIN LIFE": "https://www.zara.com/us/en/z-join-life-mkt1399.html",
      "STORES": "https://www.zara.com/us/en/z-stores-st1404.html",
      "PERFUMES": "https://www.zara.com/us/en/woman-accessories-perfumes-l1017.html?v1=2419833",
      "MAKEUP": "https://www.zara.com/us/en/woman-beauty-makeup-l4414.html?v1=1881272",
      "ZARA HAIR": "https://www.zara.com/us/en/woman-hair-l7345.html?v1=2418886",
      "ABOUT": "https://www.zara.com/us/en/zara-travel-about-mkt15716.html",
      "REPAIR": "https://www.zara.com/us/en/preowned-repair-mkt5796.html",
      "SECOND HAND": "https://www.zara.com/us/en/preowned-resell-mkt5797.html",
      "DONATE": "https://www.zara.com/us/en/preowned-donate-mkt5798.html",
      "THE GUIDES": "https://www.zara.com/us/en/zara-travel-guide-mkt15717.html",
      "Youtube": "http://www.youtube.com/user/zara",
      "Spotify": "https://open.spotify.com/user/r6ivwuv0ebk346hhxo446pbfv"
    },
    "aria_length": 19276,
    "aria_preview": "- link \"Skip to main content\":\n  - /url: \"#main\"\n- banner:\n  - button \"Close menu\"\n  - link \"Go to homepage\":\n    - /url: https://www.zara.com/us/\n  - list:\n    - listitem:\n      - link \"Search\":\n        - /url: https://www.zara.com/us/en/search/home\n    - listitem:\n      - link \"LOG IN\":\n        - /url: https://www.zara.com/us/en/logon\n    - listitem:\n      - link \"Help\":\n        - /url: https://www.zara.com/us/en/help-center\n    - listitem:\n      - link \"Cart empty\":\n        - /url: https://ww..."
  }
]